labscheduler/__init__.py
labscheduler/config.py
labscheduler/logging_manager.py
labscheduler/scheduler_implementation.py
labscheduler/scheduler_interface.py
labscheduler/solver_interface.py
labscheduler/structures.py
labscheduler/utilities.py
labscheduler/dev_tools/__init__.py
labscheduler/dev_tools/algorithms_eval.py
labscheduler/dev_tools/algorithms_eval_config.py
labscheduler/dev_tools/check_cp_instance.py
labscheduler/dev_tools/eval_schedule.py
labscheduler/dev_tools/prefect_poc.py
labscheduler/dev_tools/schedule_problem.py
labscheduler/dev_tools/utilities.py
labscheduler/dev_tools/table/data_no_heur.json
labscheduler/dev_tools/table/data_with_heur.json
labscheduler/dev_tools/table/table.tex
labscheduler/sila_server/__init__.py
labscheduler/sila_server/__main__.py
labscheduler/sila_server/server.py
labscheduler/sila_server/fdl_files/LabConfigurationController.sila.xml
labscheduler/sila_server/fdl_files/SchedulingService.sila.xml
labscheduler/sila_server/feature_implementations/__init__.py
labscheduler/sila_server/feature_implementations/labconfigurationcontroller_impl.py
labscheduler/sila_server/feature_implementations/schedulingservice_impl.py
labscheduler/sila_server/generated/__init__.py
labscheduler/sila_server/generated/client.py
labscheduler/sila_server/generated/labconfigurationcontroller/LabConfigurationController.proto
labscheduler/sila_server/generated/labconfigurationcontroller/LabConfigurationController.sila.xml
labscheduler/sila_server/generated/labconfigurationcontroller/__init__.py
labscheduler/sila_server/generated/labconfigurationcontroller/labconfigurationcontroller_base.py
labscheduler/sila_server/generated/labconfigurationcontroller/labconfigurationcontroller_client.py
labscheduler/sila_server/generated/labconfigurationcontroller/labconfigurationcontroller_errors.py
labscheduler/sila_server/generated/labconfigurationcontroller/labconfigurationcontroller_feature.py
labscheduler-0.2.43.dist-info/METADATA
labscheduler-0.2.43.dist-info/WHEEL
labscheduler-0.2.43.dist-info/entry_points.txt
labscheduler-0.2.43.dist-info/licenses/LICENSE
labscheduler-0.2.43.dist-info/RECORD
