Metadata-Version: 2.4
Name: labscheduler
Version: 0.2.43
Summary: The python lab scheduler is an adaptive scheduler solving generalized (suited to lab demands) versions of the JSSP (Job Shop Scheduling Problem). It comes as a microservice with a SiLA and a python interface.
Project-URL: Homepage, https://gitlab.com/opensourcelab/labscheduler
Author-email: Stefan Maak <stefanmaak@freenet.de>, Dani Bodor <d.bodor@esciencecenter.nl>, Djura Smits <D.Smits@esciencecenter.nl>, Walter Baccinelli <w.baccinelli@esciencecenter.nl>, Mark Doerr <mark.doerr@uni-greifswald.de>
License: MIT
License-File: LICENSE
Classifier: Development Status :: 4 - Beta
Classifier: Intended Audience :: Developers
Classifier: Intended Audience :: Education
Classifier: Intended Audience :: Science/Research
Classifier: License :: OSI Approved :: MIT License
Classifier: Natural Language :: English
Classifier: Operating System :: OS Independent
Classifier: Programming Language :: Python :: 3
Classifier: Programming Language :: Python :: 3.11
Classifier: Programming Language :: Python :: 3.12
Classifier: Topic :: Scientific/Engineering
Classifier: Topic :: Scientific/Engineering :: Bio-Informatics
Classifier: Topic :: Scientific/Engineering :: Chemistry
Classifier: Topic :: Scientific/Engineering :: Information Analysis
Classifier: Topic :: Scientific/Engineering :: Visualization
Requires-Python: >=3.11
Requires-Dist: grpcio-tools==1.71.0
Requires-Dist: grpcio==1.71.0
Requires-Dist: networkx>=3.1
Requires-Dist: protobuf==5.29.4
Requires-Dist: pytz>=2023.3
Requires-Dist: pyyaml>=6.0.1
Requires-Dist: sila2>=0.12
